dismod/__init__.py
dismod/__main__.py
dismod/dependency.py
dismod/dot.py
dismod/instruction.py
dismod/main.py
dismod/utils.py
dismod-0.3.0.dist-info/LICENSE
dismod-0.3.0.dist-info/METADATA
dismod-0.3.0.dist-info/WHEEL
dismod-0.3.0.dist-info/entry_points.txt
dismod-0.3.0.dist-info/top_level.txt
dismod-0.3.0.dist-info/RECORD
