Metadata-Version: 2.1
Name: dismod
Version: 0.3.0
Summary: Generate dependency graphs for your modules
Home-page: https://github.com/r0x0d/dismod
Author: Rodolfo Olivieri
Author-email: rodolfo.olivieri3@gmail.com
License: MIT
Classifier: License :: OSI Approved :: MIT License
Classifier: Programming Language :: Python :: 3
Classifier: Programming Language :: Python :: 3 :: Only
Classifier: Programming Language :: Python :: Implementation :: CPython
Classifier: Programming Language :: Python :: Implementation :: PyPy
Requires-Python: >=3.7
License-File: LICENSE
